odoo/addons/project_multi_company/README.rst
odoo/addons/project_multi_company/__init__.py
odoo/addons/project_multi_company/__manifest__.py
odoo/addons/project_multi_company/i18n/fr.po
odoo/addons/project_multi_company/i18n/it.po
odoo/addons/project_multi_company/i18n/project_multi_company.pot
odoo/addons/project_multi_company/models/__init__.py
odoo/addons/project_multi_company/models/project_project_stage.py
odoo/addons/project_multi_company/models/project_task_type.py
odoo/addons/project_multi_company/readme/CONTRIBUTORS.rst
odoo/addons/project_multi_company/readme/DESCRIPTION.rst
odoo/addons/project_multi_company/security/ir_rule.xml
odoo/addons/project_multi_company/static/description/icon.png
odoo/addons/project_multi_company/static/description/index.html
odoo/addons/project_multi_company/views/view_project_project_stage.xml
odoo/addons/project_multi_company/views/view_project_task_type.xml
odoo_addon_project_multi_company-16.0.1.0.0.5.dist-info/METADATA
odoo_addon_project_multi_company-16.0.1.0.0.5.dist-info/WHEEL
odoo_addon_project_multi_company-16.0.1.0.0.5.dist-info/top_level.txt
odoo_addon_project_multi_company-16.0.1.0.0.5.dist-info/RECORD
